PyPokeClasses/__init__.py
PyPokeClasses/py.typed
PyPokeClasses/Berries/Berry.py
PyPokeClasses/Berries/BerryFirmness.py
PyPokeClasses/Berries/BerryFlavor.py
PyPokeClasses/Berries/__init__.py
PyPokeClasses/Contests/ContestEffect.py
PyPokeClasses/Contests/ContestType.py
PyPokeClasses/Contests/SuperContestEffect.py
PyPokeClasses/Contests/__init__.py
PyPokeClasses/Encounters/EncounterCondition.py
PyPokeClasses/Encounters/EncounterConditionValue.py
PyPokeClasses/Encounters/EncounterMethod.py
PyPokeClasses/Encounters/__init__.py
PyPokeClasses/Evolution/EvolutionChain.py
PyPokeClasses/Evolution/EvolutionTrigger.py
PyPokeClasses/Evolution/__init__.py
PyPokeClasses/Games/Generation.py
PyPokeClasses/Games/Pokedex.py
PyPokeClasses/Games/Version.py
PyPokeClasses/Games/VersionGroup.py
PyPokeClasses/Games/__init__.py
PyPokeClasses/Items/Item.py
PyPokeClasses/Items/ItemAttribute.py
PyPokeClasses/Items/ItemCategory.py
PyPokeClasses/Items/ItemFlingEffect.py
PyPokeClasses/Items/ItemPocket.py
PyPokeClasses/Items/__init__.py
PyPokeClasses/Locations/Location.py
PyPokeClasses/Locations/LocationArea.py
PyPokeClasses/Locations/PalParkArea.py
PyPokeClasses/Locations/Region.py
PyPokeClasses/Locations/__init__.py
PyPokeClasses/Machines/Machine.py
PyPokeClasses/Machines/__init__.py
PyPokeClasses/Moves/MoveAilments.py
PyPokeClasses/Moves/MoveBattleStyles.py
PyPokeClasses/Moves/MoveCategory.py
PyPokeClasses/Moves/MoveDamageClass.py
PyPokeClasses/Moves/MoveLearnMethod.py
PyPokeClasses/Moves/MoveTarget.py
PyPokeClasses/Moves/Moves.py
PyPokeClasses/Moves/__init__.py
PyPokeClasses/Pokemon/Abilities.py
PyPokeClasses/Pokemon/Characteristic.py
PyPokeClasses/Pokemon/EggGroup.py
PyPokeClasses/Pokemon/Genders.py
PyPokeClasses/Pokemon/GrowthRate.py
PyPokeClasses/Pokemon/Natures.py
PyPokeClasses/Pokemon/PokeathlonStats.py
PyPokeClasses/Pokemon/Pokemon.py
PyPokeClasses/Pokemon/PokemonColors.py
PyPokeClasses/Pokemon/PokemonForms.py
PyPokeClasses/Pokemon/PokemonHabitats.py
PyPokeClasses-0.1.18.dist-info/LICENSE
PyPokeClasses-0.1.18.dist-info/METADATA
PyPokeClasses-0.1.18.dist-info/WHEEL
PyPokeClasses-0.1.18.dist-info/top_level.txt
PyPokeClasses-0.1.18.dist-info/RECORD
