Metadata-Version: 2.1
Name: PyPokeClasses
Version: 0.1.18
Summary: A class-based Package for accessing and interacting with PokeAPI's JSON data.
Home-page: https://github.com/atama12/PyPokeClasses.git
Author: Atama12
Author-email: atama5860@gmail.com
Keywords: PyPokeClasses pypokeclasses pokeAPI
Classifier: Programming Language :: Python :: 3
Classifier: Programming Language :: Python :: 3.8
Classifier: Programming Language :: Python :: 3.9
Classifier: Programming Language :: Python :: 3.10
Classifier: Programming Language :: Python :: 3.11
Classifier: Programming Language :: Python :: 3.12
Classifier: Programming Language :: Python :: 3 :: Only
Classifier: License :: OSI Approved :: MIT License
Classifier: Operating System :: OS Independent
Requires-Python: >=3.8
License-File: LICENSE
Requires-Dist: requests
Requires-Dist: typing
